LICENSE
README.md
setup.py
sub2sub/__init__.py
sub2sub/dataloader.py
sub2sub/utils.py
sub2sub.egg-info/PKG-INFO
sub2sub.egg-info/SOURCES.txt
sub2sub.egg-info/dependency_links.txt
sub2sub.egg-info/not-zip-safe
sub2sub.egg-info/requires.txt
sub2sub.egg-info/top_level.txt