Metadata-Version: 2.1
Name: sub2sub
Version: 2024.7.15
Summary: s2s: utilities for Sub2Sub
Home-page: https://github.com/fzhu2e/sub2sub-utils
Author: Feng Zhu
Author-email: fengzhu@ucar.edu
License: MIT
Keywords: Sub2Sub,OMIP
Classifier: Natural Language :: English
Classifier: Programming Language :: Python :: 3.11
Classifier: Programming Language :: Python :: 3.12
License-File: LICENSE
Requires-Dist: netCDF4
Requires-Dist: xarray
Requires-Dist: dask
Requires-Dist: nc-time-axis
Requires-Dist: colorama
Requires-Dist: tqdm
